LICENSE
setup.py
BayesGM/__init__.py
BayesGM/__main__.py
BayesGM/bayesGM.py
BayesGM/cli.py
BayesGM/model.py
BayesGM/util.py
CausalBGM.egg-info/PKG-INFO
CausalBGM.egg-info/SOURCES.txt
CausalBGM.egg-info/dependency_links.txt
CausalBGM.egg-info/entry_points.txt
CausalBGM.egg-info/requires.txt
CausalBGM.egg-info/top_level.txt