Metadata-Version: 2.1
Name: CausalBGM
Version: 0.1.3
Summary: CausalBGM: An AI-powered Bayesian generative modeling approach for causal inference in observational studies
Home-page: https://github.com/SUwonglab/CausalBGM
Author: Qiao Liu
Author-email: liuqiao@stanford.edu
Classifier: Programming Language :: Python :: 3
Classifier: License :: OSI Approved :: MIT License
Classifier: Operating System :: OS Independent
Requires-Python: >=3.9
License-File: LICENSE
